<?xml version="1.0" encoding="utf-8"?>
<odoo>
    <record id="view_edit_project_form_ext" model="ir.ui.view">
        <field name="name">view.edit.project.form.ext</field>
        <field name="model">project.project</field>
        <field name="inherit_id" ref="project.edit_project"/>
        <field name="arch" type="xml">
            <xpath expr="//field[@name='user_id']" position="after">
                <field name="subscriber_location_id"/>
                <field name="subscription_count"/>
            </xpath>

            <xpath expr="//field[@name='analytic_account_id']" position="attributes">
                <attribute name="invisible">True</attribute>
            </xpath>
        </field>
    </record>

</odoo>
