<?xml version="1.0" encoding="utf-8"?>
<odoo>
    <record id="view_sale_subscription_form" model="ir.ui.view">
        <field name="name">view.sale.subscription.form</field>
        <field name="model">sale.subscription</field>
        <field name="inherit_id" ref="sale_subscription.sale_subscription_view_form"/>
        <field name="arch" type="xml">
            <xpath expr="//field[@name='partner_id']" position="before">
                <field name="account_identification"/>
            </xpath>
          
            <xpath expr="//field[@name='date_start']" position="before">
                <field name="subscription_status"/>
            </xpath>

            <xpath expr="//field[@name='code']" position="after">
                <field name="opportunity_id" readonly="1"/>
            </xpath>

            <xpath expr="//field[@name='price_subtotal']" position="after">
                <field name="date_start" optional="show" attrs="{}"/>
                <field name="date_end" optional="show" attrs="{}"/>
            </xpath>
            <xpath expr="//form[1]/sheet[1]/div[not(@name)][3]/notebook[1]/page[1]/div[1]/field[@name='recurring_invoice_line_ids']/form[1]/group[1]/group[1]/field[@name='price_unit']" position="after">
                <field name="date_start" attrs="{}"/>
                <field name="date_end" attrs="{}"/>
            </xpath>
        </field>
    </record>

</odoo>
